__init__.py
std_methods/__init__.py
std_methods/factories/__init__.py
std_methods/factories/diagram_factory.py
std_methods/factories/node_factory.py
std_methods/factories/relationship_factory.py
std_methods/repositories/__init__.py
std_methods/repositories/base_repository.py
std_methods/utils/__init__.py
std_methods/utils/id_generator.py
tests/test_base_repository.py
tests/test_diagram_factory.py
tests/test_id_generator.py
tests/test_node_factory.py
tests/test_relationship_factory.py
std_methods-0.1.2.dist-info/METADATA
std_methods-0.1.2.dist-info/WHEEL
std_methods-0.1.2.dist-info/top_level.txt
std_methods-0.1.2.dist-info/RECORD
