Metadata-Version: 2.2
Name: std_methods
Version: 0.1.2
Summary: A central repository for shared logic and utilities across the tool's microservices.
Author-email: Mattyboy <meowmew@cat.com>
Requires-Python: >=3.13
Requires-Dist: build>=1.2.2.post1
Requires-Dist: neo4j>=5.28.1
Requires-Dist: pytest>=8.3.5
Requires-Dist: ruff>=0.9.10
Requires-Dist: twine>=6.1.0
